text_hammer/__init__.py
text_hammer/utils.py
text_hammer/data/abbreviations_wordlist.json
text_hammer-0.1.5.dist-info/LICENSE
text_hammer-0.1.5.dist-info/METADATA
text_hammer-0.1.5.dist-info/WHEEL
text_hammer-0.1.5.dist-info/top_level.txt
text_hammer-0.1.5.dist-info/RECORD
