Metadata-Version: 2.1
Name: text-hammer
Version: 0.1.5
Summary: This is text preprocessing package
Home-page: UNKNOWN
Author: Abhishek Jaiswal
Author-email: abhishek.jaiswal26102001@gmail.com
License: Apache License 2.0
Platform: UNKNOWN
Requires-Dist: beautifulsoup4 (==4.9.1)
Requires-Dist: pandas
Requires-Dist: numpy
Requires-Dist: spacy
Requires-Dist: TextBlob
